mcdata_to_json/__init__.py
mcdata_to_json/__main__.py
mcdata_to_json/__version__.py
mcdata_to_json/configuration.py
mcdata_to_json/dat_exporter.py
mcdata_to_json/error_handling.py
mcdata_to_json/mca_parser.py
mcdata_to_json/mojang_api.py
mcdata_to_json/player.py
mcdata_to_json/tools.py
mcdata_to_json/logs/__init__.py
mcdata_to_json/logs/combiner.py
mcdata_to_json/logs/parser.py
mcdata_to_json/logs/splitter.py
mcdata_to_json/logs/type_defs.py
mcdata_to_json/mcdata/__init__.py
mcdata_to_json/mcdata/advancements.py
mcdata_to_json/mcdata/biome_dictionary.py
mcdata_to_json/mcdata/data_extractor.py
mcdata_to_json/mcdata/data_packs.py
mcdata_to_json/mcdata/mca_reader.py
mcdata_to_json/mcdata/server_downloader.py
mcdata_to_json-0.4.0.0.dist-info/LICENSE
mcdata_to_json-0.4.0.0.dist-info/METADATA
mcdata_to_json-0.4.0.0.dist-info/WHEEL
mcdata_to_json-0.4.0.0.dist-info/top_level.txt
mcdata_to_json-0.4.0.0.dist-info/RECORD
